{"P3": {"labels": ["python"], "postTitle": "python\u57fa\u7840", "postUrl": "post/python-ji-chu.html", "createdDate": "2024-12-16", "dateLabelColor": "#bc4c00"}, "P2": {"labels": ["python"], "postTitle": "\u6d4b\u8bd5", "postUrl": "post/ce-shi.html", "createdDate": "2024-11-20", "dateLabelColor": "#bc4c00"}, "labelColorDict": {"bug": "#d73a4a", "duplicate": "#cfd3d7", "enhancement": "#a2eeef", "good first issue": "#7057ff", "help wanted": "#008672", "invalid": "#e4e669", "python": "#0075ca", "question": "#d876e3", "wontfix": "#ffffff"}}